dmri_rcnn/__init__.py
dmri_rcnn/bin/__init__.py
dmri_rcnn/bin/dmri_rcnn_download_all_weights.py
dmri_rcnn/bin/dmri_sh_baseline.py
dmri_rcnn/bin/run_dmri_rcnn.py
dmri_rcnn/core/__init__.py
dmri_rcnn/core/io.py
dmri_rcnn/core/weights.py
dmri_rcnn/core/model/__init__.py
dmri_rcnn/core/model/autoencoder.py
dmri_rcnn/core/model/layers.py
dmri_rcnn/core/processing/__init__.py
dmri_rcnn/core/processing/sph_harmonic.py
dmri_rcnn/core/processing/inference/__init__.py
dmri_rcnn/core/processing/inference/base.py
dmri_rcnn/core/processing/inference/patcher.py
dmri_rcnn/core/processing/inference/processor.py
dmri_rcnn/core/processing/inference/reshaper.py
dmri_rcnn/core/processing/inference/scaler.py
dmri_rcnn/core/processing/training/__init__.py
dmri_rcnn/core/processing/training/base.py
dmri_rcnn/core/processing/training/io.py
dmri_rcnn/core/processing/training/patcher.py
dmri_rcnn/core/processing/training/processor.py
dmri_rcnn/core/processing/training/reshaper.py
dmri_rcnn/core/processing/training/scaler.py
dmri_rcnn/core/processing/training/shell_filter.py
dmri_rcnn/core/processing/training/shell_reorder.py
dmri_rcnn/core/processing/training/utils.py
dmri_rcnn-0.4.2.data/scripts/dmri_rcnn_download_all_weights.py
dmri_rcnn-0.4.2.data/scripts/dmri_sh_baseline.py
dmri_rcnn-0.4.2.data/scripts/run_dmri_rcnn.py
dmri_rcnn-0.4.2.dist-info/LICENSE
dmri_rcnn-0.4.2.dist-info/METADATA
dmri_rcnn-0.4.2.dist-info/WHEEL
dmri_rcnn-0.4.2.dist-info/top_level.txt
dmri_rcnn-0.4.2.dist-info/RECORD
