Metadata-Version: 2.2
Name: dmri-rcnn
Version: 0.4.2
Summary: Diffusion MRI Recurrent CNN for Angular Super-resolution.
Home-page: https://github.com/m-lyon/dMRI-RCNN
Download-URL: https://github.com/m-lyon/dMRI-RCNN/archive/v0.4.2.tar.gz
Author: Matthew Lyon
Author-email: matthewlyon18@gmail.com
License: MIT License
Keywords: ai,cv,computer-vision,mri,dmri,super-resolution,cnn
Classifier: Programming Language :: Python
Classifier: Operating System :: Unix
Classifier: Operating System :: MacOS
Classifier: Operating System :: Microsoft :: Windows :: Windows 10
Requires-Python: >=3.8
License-File: LICENSE
Requires-Dist: tensorflow<2.8,>=2.6
Requires-Dist: numpy
Requires-Dist: einops
Requires-Dist: nibabel
Requires-Dist: tqdm
Provides-Extra: sh
Requires-Dist: dipy; extra == "sh"
Dynamic: author
Dynamic: author-email
Dynamic: classifier
Dynamic: description
Dynamic: description-content-type
Dynamic: download-url
Dynamic: home-page
Dynamic: keywords
Dynamic: license
Dynamic: provides-extra
Dynamic: requires-dist
Dynamic: requires-python
Dynamic: summary
